[
    {
        "id": "bach023",
        "is_live": false
    },
    {
        "id": "doki0818",
        "is_live": false
    },
    {
        "id": "xpdpfv2",
        "is_live": false
    },
    {
        "id": "ducke77",
        "is_live": false
    },
    {
        "id": "joaras2",
        "is_live": false
    },
    {
        "id": "gyeonjahee",
        "is_live": false
    },
    {
        "id": "melodingding",
        "is_live": false
    },
    {
        "id": "soyoung6056",
        "is_live": false
    },
    {
        "id": "akdma9692",
        "is_live": false
    },
    {
        "id": "nlov555jij",
        "is_live": false
    },
    {
        "id": "gatgdf",
        "is_live": true,
        "title": "[고래상사] 멸망전 연습 w.찌로리.댕뚜비",
        "viewers": 70,
        "thumbnail": "https://liveimg.afreecatv.com/m/290382570",
        "live_url": "https://play.sooplive.co.kr/gatgdf/290382570"
    },
    {
        "id": "kimmaren77",
        "is_live": false
    },
    {
        "id": "dmng50",
        "is_live": true,
        "title": "[고래상사] 새해 마지막날 땅콩이 와써용",
        "viewers": 108,
        "thumbnail": "https://liveimg.afreecatv.com/m/290381510",
        "live_url": "https://play.sooplive.co.kr/dmng50/290381510"
    },
    {
        "id": "nunknown314",
        "is_live": false
    }
]